{"cameraMode":{"drawMode":0,"name":"Shaded","section":"Shading Mode"},"sceneLighting":true,"audioPlay":false,"sceneViewState":{"m_AlwaysRefresh":false,"showFog":true,"showSkybox":true,"showFlares":true,"showImageEffects":true,"showParticleSystems":true,"showVisualEffectGraphs":true,"m_FxEnabled":false},"in2DMode":false,"pivot":{"x":1067.62109375,"y":-1118.2568359375,"z":1931.69580078125},"rotation":{"x":-0.3024075925350189,"y":-0.1684052050113678,"z":0.05437403544783592,"w":-0.9366070032119751},"size":967.248291015625,"orthographic":false}